ssb_libtest78/__init__.py
ssb_libtest78/__main__.py
ssb_libtest78/functions.py
ssb_libtest78/py.typed
ssb_libtest78-0.0.1.dist-info/LICENSE
ssb_libtest78-0.0.1.dist-info/METADATA
ssb_libtest78-0.0.1.dist-info/WHEEL
ssb_libtest78-0.0.1.dist-info/entry_points.txt
ssb_libtest78-0.0.1.dist-info/RECORD
